{
    "props": {
        "pageProps": {
            "query": {
                "id": "1376620d9137402e94ac1c959558f146"
            },
            "ieBrowser": false,
            "needRefresh": false,
            "writingDetail": {
                "id": 85265,
                "outId": "1376620d9137402e94ac1c959558f146",
                "articleOutId": "1376620d9137402e94ac1c959558f146",
                "html": "<h1 data-tool=\"mdnice编辑器\" style=\"margin-top: 30px; margin-bottom: 15px; padding: 0px; font-weight: bold; color: black; font-size: 24px;\"><span class=\"prefix\" style=\"display: none;\"></span><span class=\"content\">多元时间序列预测的动态模式分解</span><span class=\"suffix\"></span></h1> \n<p data-tool=\"mdnice编辑器\" style=\"padding-top: 8px; padding-bottom: 8px; margin: 0; line-height: 26px; color: black; font-size: 17px; word-spacing: 3px; letter-spacing: 1px;\">动态模式分解 (DMD) 是一种数据驱动的降维算法，由<em style=\"font-style: italic; color: black;\">Peter Schmid</em>于 2008 年开发</p> \n<p data-tool=\"mdnice编辑器\" style=\"padding-top: 8px; padding-bottom: 8px; margin: 0; line-height: 26px; color: black; font-size: 17px; word-spacing: 3px; letter-spacing: 1px;\">类似于矩阵分解和主成分分析 (PCA) 算法。给定一个多变量时间序列数据集，DMD 计算一组动态模式，其中每个模式都与固定的振荡频率和衰减/增长率相关联。由于每个动态模式的内在时间行为，DMD 确实不同于 PCA 等常用的降维算法。DMD 允许人们用物理上有意义的模式来解释数据的时间行为。一个重要特性是 DMD 能够执行多变量时间序列预测。</p> \n<p data-tool=\"mdnice编辑器\" style=\"padding-top: 8px; padding-bottom: 8px; margin: 0; line-height: 26px; color: black; font-size: 17px; word-spacing: 3px; letter-spacing: 1px;\">在本文中，我们将介绍 DMD 算法的初步知识，并讨论如何使用 Numpy 在 Python 中重现 DMD。并给一个地学实例。</p> \n<h2 data-tool=\"mdnice编辑器\" style=\"margin-top: 30px; margin-bottom: 15px; padding: 0px; font-weight: bold; color: black; font-size: 22px;\"><span class=\"prefix\" style=\"display: none;\"></span><span class=\"content\" style=\"background-color: #F7D3CC; color: #FFF; padding: 5px 15px; border-radius: 1px;\">原理</span><span class=\"suffix\"></span></h2> \n<p data-tool=\"mdnice编辑器\" style=\"padding-top: 8px; padding-bottom: 8px; margin: 0; line-height: 26px; color: black; font-size: 17px; word-spacing: 3px; letter-spacing: 1px;\">DMD 与向量自回归 (VAR) 模型有很强的联系。VAR 是一种经典统计模型，用于捕捉多元时间序列数据的共同演化模式</p> \n<p data-tool=\"mdnice编辑器\" style=\"padding-top: 8px; padding-bottom: 8px; margin: 0; line-height: 26px; color: black; font-size: 17px; word-spacing: 3px; letter-spacing: 1px;\">其中<em style=\"font-style: italic; color: black;\">N</em>是变量数，<em style=\"font-style: italic; color: black;\">T</em>是时间步数，那么在任何时间步<em style=\"font-style: italic; color: black;\">t</em>中，一阶 VAR 或 VAR(1) 的形式为</p> <span class=\"span-block-equation\" style=\"cursor:pointer\" data-tool=\"mdnice编辑器\"> \n <section class=\"block-equation\" width=\"full\" role=\"presentation\" data-formula=\"\\begin{equation}\nx_t = A x_{t-1} + \\epsilon_t\n\\end{equation}\n\n\" data-formula-type=\"block-equation\" style=\"display: block; text-align: center; overflow: auto; display: block; -webkit-overflow-scrolling: touch; min-width: 24.506ex; position: relative;\"> \n  <svg xmlns=\"http://www.w3.org/2000/svg\" role=\"img\" focusable=\"false\" aria-hidden=\"true\" style=\"-webkit-overflow-scrolling: touch; vertical-align: -0.566ex; min-width: 24.506ex; width: 100%; height: 2.262ex; max-width: 300% !important;\"> <g stroke=\"currentColor\" fill=\"currentColor\" stroke-width=\"0\" transform=\"matrix(1 0 0 -1 0 0) scale(0.016893) translate(0, -750)\"> \n    <g data-mml-node=\"math\"> \n     <g data-mml-node=\"mtable\" transform=\"translate(2078, 0) translate(-2078, 0)\"> \n      <g transform=\"translate(0 750) matrix(1 0 0 -1 0 0) scale(59.2)\"> \n       <svg data-table=\"true\" preserveaspectratio=\"xMidYMid\" viewbox=\"3337.7 -750 1 1000\" style=\"-webkit-overflow-scrolling: touch; max-width: 300% !important;\"> <g transform=\"matrix(1 0 0 -1 0 0)\"> \n         <g data-mml-node=\"mlabeledtr\"> \n          <g data-mml-node=\"mtd\"> \n           <g data-mml-node=\"msub\"> \n            <g data-mml-node=\"mi\"> \n             <path data-c=\"1D465\" d=\"M52 289Q59 331 106 386T222 442Q257 442 286 424T329 379Q371 442 430 442Q467 442 494 420T522 361Q522 332 508 314T481 292T458 288Q439 288 427 299T415 328Q415 374 465 391Q454 404 425 404Q412 404 406 402Q368 386 350 336Q290 115 290 78Q290 50 306 38T341 26Q378 26 414 59T463 140Q466 150 469 151T485 153H489Q504 153 504 145Q504 144 502 134Q486 77 440 33T333 -11Q263 -11 227 52Q186 -10 133 -10H127Q78 -10 57 16T35 71Q35 103 54 123T99 143Q142 143 142 101Q142 81 130 66T107 46T94 41L91 40Q91 39 97 36T113 29T132 26Q168 26 194 71Q203 87 217 139T245 247T261 313Q266 340 266 352Q266 380 251 392T217 404Q177 404 142 372T93 290Q91 281 88 280T72 278H58Q52 284 52 289Z\" /> \n            </g> \n            <g data-mml-node=\"mi\" transform=\"translate(572, -150) scale(0.707)\"> \n             <path data-c=\"1D461\" d=\"M26 385Q19 392 19 395Q19 399 22 411T27 425Q29 430 36 430T87 431H140L159 511Q162 522 166 540T173 566T179 586T187 603T197 615T211 624T229 626Q247 625 254 615T261 596Q261 589 252 549T232 470L222 433Q222 431 272 431H323Q330 424 330 420Q330 398 317 385H210L174 240Q135 80 135 68Q135 26 162 26Q197 26 230 60T283 144Q285 150 288 151T303 153H307Q322 153 322 145Q322 142 319 133Q314 117 301 95T267 48T216 6T155 -11Q125 -11 98 4T59 56Q57 64 57 83V101L92 241Q127 382 128 383Q128 385 77 385H26Z\" /> \n            </g> \n           </g> \n           <g data-mml-node=\"mo\" transform=\"translate(1155, 0)\"> \n            <path data-c=\"3D\" d=\"M56 347Q56 360 70 367H707Q722 359 722 347Q722 336 708 328L390 327H72Q56 332 56 347ZM56 153Q56 168 72 173H708Q722 163 722 153Q722 140 707 133H70Q56 140 56 153Z\" /> \n           </g> \n           <g data-mml-node=\"mi\" transform=\"translate(2210.8, 0)\"> \n            <path data-c=\"1D434\" d=\"M208 74Q208 50 254 46Q272 46 272 35Q272 34 270 22Q267 8 264 4T251 0Q249 0 239 0T205 1T141 2Q70 2 50 0H42Q35 7 35 11Q37 38 48 46H62Q132 49 164 96Q170 102 345 401T523 704Q530 716 547 716H555H572Q578 707 578 706L606 383Q634 60 636 57Q641 46 701 46Q726 46 726 36Q726 34 723 22Q720 7 718 4T704 0Q701 0 690 0T651 1T578 2Q484 2 455 0H443Q437 6 437 9T439 27Q443 40 445 43L449 46H469Q523 49 533 63L521 213H283L249 155Q208 86 208 74ZM516 260Q516 271 504 416T490 562L463 519Q447 492 400 412L310 260L413 259Q516 259 516 260Z\" /> \n           </g> \n           <g data-mml-node=\"msub\" transform=\"translate(2960.8, 0)\"> \n            <g data-mml-node=\"mi\"> \n             <path data-c=\"1D465\" d=\"M52 289Q59 331 106 386T222 442Q257 442 286 424T329 379Q371 442 430 442Q467 442 494 420T522 361Q522 332 508 314T481 292T458 288Q439 288 427 299T415 328Q415 374 465 391Q454 404 425 404Q412 404 406 402Q368 386 350 336Q290 115 290 78Q290 50 306 38T341 26Q378 26 414 59T463 140Q466 150 469 151T485 153H489Q504 153 504 145Q504 144 502 134Q486 77 440 33T333 -11Q263 -11 227 52Q186 -10 133 -10H127Q78 -10 57 16T35 71Q35 103 54 123T99 143Q142 143 142 101Q142 81 130 66T107 46T94 41L91 40Q91 39 97 36T113 29T132 26Q168 26 194 71Q203 87 217 139T245 247T261 313Q266 340 266 352Q266 380 251 392T217 404Q177 404 142 372T93 290Q91 281 88 280T72 278H58Q52 284 52 289Z\" /> \n            </g> \n            <g data-mml-node=\"TeXAtom\" transform=\"translate(572, -150) scale(0.707)\" data-mjx-texclass=\"ORD\"> \n             <g data-mml-node=\"mi\"> \n              <path data-c=\"1D461\" d=\"M26 385Q19 392 19 395Q19 399 22 411T27 425Q29 430 36 430T87 431H140L159 511Q162 522 166 540T173 566T179 586T187 603T197 615T211 624T229 626Q247 625 254 615T261 596Q261 589 252 549T232 470L222 433Q222 431 272 431H323Q330 424 330 420Q330 398 317 385H210L174 240Q135 80 135 68Q135 26 162 26Q197 26 230 60T283 144Q285 150 288 151T303 153H307Q322 153 322 145Q322 142 319 133Q314 117 301 95T267 48T216 6T155 -11Q125 -11 98 4T59 56Q57 64 57 83V101L92 241Q127 382 128 383Q128 385 77 385H26Z\" /> \n             </g> \n             <g data-mml-node=\"mo\" transform=\"translate(361, 0)\"> \n              <path data-c=\"2212\" d=\"M84 237T84 250T98 270H679Q694 262 694 250T679 230H98Q84 237 84 250Z\" /> \n             </g> \n             <g data-mml-node=\"mn\" transform=\"translate(1139, 0)\"> \n              <path data-c=\"31\" d=\"M213 578L200 573Q186 568 160 563T102 556H83V602H102Q149 604 189 617T245 641T273 663Q275 666 285 666Q294 666 302 660V361L303 61Q310 54 315 52T339 48T401 46H427V0H416Q395 3 257 3Q121 3 100 0H88V46H114Q136 46 152 46T177 47T193 50T201 52T207 57T213 61V578Z\" /> \n             </g> \n            </g> \n           </g> \n           <g data-mml-node=\"mo\" transform=\"translate(4964, 0)\"> \n            <path data-c=\"2B\" d=\"M56 237T56 250T70 270H369V420L370 570Q380 583 389 583Q402 583 409 568V270H707Q722 262 722 250T707 230H409V-68Q401 -82 391 -82H389H387Q375 -82 369 -68V230H70Q56 237 56 250Z\" /> \n           </g> \n           <g data-mml-node=\"msub\" transform=\"translate(5964.2, 0)\"> \n            <g data-mml-node=\"mi\"> \n             <path data-c=\"1D716\" d=\"M227 -11Q149 -11 95 41T40 174Q40 262 87 322Q121 367 173 396T287 430Q289 431 329 431H367Q382 426 382 411Q382 385 341 385H325H312Q191 385 154 277L150 265H327Q340 256 340 246Q340 228 320 219H138V217Q128 187 128 143Q128 77 160 52T231 26Q258 26 284 36T326 57T343 68Q350 68 354 58T358 39Q358 36 357 35Q354 31 337 21T289 0T227 -11Z\" /> \n            </g> \n            <g data-mml-node=\"mi\" transform=\"translate(406, -150) scale(0.707)\"> \n             <path data-c=\"1D461\" d=\"M26 385Q19 392 19 395Q19 399 22 411T27 425Q29 430 36 430T87 431H140L159 511Q162 522 166 540T173 566T179 586T187 603T197 615T211 624T229 626Q247 625 254 615T261 596Q261 589 252 549T232 470L222 433Q222 431 272 431H323Q330 424 330 420Q330 398 317 385H210L174 240Q135 80 135 68Q135 26 162 26Q197 26 230 60T283 144Q285 150 288 151T303 153H307Q322 153 322 145Q322 142 319 133Q314 117 301 95T267 48T216 6T155 -11Q125 -11 98 4T59 56Q57 64 57 83V101L92 241Q127 382 128 383Q128 385 77 385H26Z\" /> \n            </g> \n           </g> \n          </g> \n         </g> \n        </g> \n       </svg> \n       <svg data-labels=\"true\" preserveaspectratio=\"xMaxYMid\" viewbox=\"1278 -750 1 1000\" style=\"-webkit-overflow-scrolling: touch; max-width: 300% !important;\"> <g data-labels=\"true\" transform=\"matrix(1 0 0 -1 0 0)\"> \n         <g data-mml-node=\"mtd\" id=\"mjx-eqn-1\"> \n          <g data-mml-node=\"mtext\"> \n           <path data-c=\"28\" d=\"M94 250Q94 319 104 381T127 488T164 576T202 643T244 695T277 729T302 750H315H319Q333 750 333 741Q333 738 316 720T275 667T226 581T184 443T167 250T184 58T225 -81T274 -167T316 -220T333 -241Q333 -250 318 -250H315H302L274 -226Q180 -141 137 -14T94 250Z\" /> \n           <path data-c=\"31\" d=\"M213 578L200 573Q186 568 160 563T102 556H83V602H102Q149 604 189 617T245 641T273 663Q275 666 285 666Q294 666 302 660V361L303 61Q310 54 315 52T339 48T401 46H427V0H416Q395 3 257 3Q121 3 100 0H88V46H114Q136 46 152 46T177 47T193 50T201 52T207 57T213 61V578Z\" transform=\"translate(389, 0)\" /> \n           <path data-c=\"29\" d=\"M60 749L64 750Q69 750 74 750H86L114 726Q208 641 251 514T294 250Q294 182 284 119T261 12T224 -76T186 -143T145 -194T113 -227T90 -246Q87 -249 86 -250H74Q66 -250 63 -250T58 -247T55 -238Q56 -237 66 -225Q221 -64 221 250T66 725Q56 737 55 738Q55 746 60 749Z\" transform=\"translate(889, 0)\" /> \n          </g> \n         </g> \n        </g> \n       </svg> \n      </g> \n     </g> \n    </g> \n   </g> \n  </svg> \n </section></span> \n<p data-tool=\"mdnice编辑器\" style=\"padding-top: 8px; padding-bottom: 8px; margin: 0; line-height: 26px; color: black; font-size: 17px; word-spacing: 3px; letter-spacing: 1px;\">在 VAR(1) 模型中，建模目标是找到一个表现良好的系数矩阵，并用它来表示时间相关性。在标准 DMD 模型中，我们也采用 VAR(1) 的形式。要计算系数，首先要将上述方程重写如下，</p> <span class=\"span-block-equation\" style=\"cursor:pointer\" data-tool=\"mdnice编辑器\"> \n <section class=\"block-equation\" role=\"presentation\" data-formula=\"X_2=AX_1\n\" data-formula-type=\"block-equation\" style=\"display: block; text-align: center; overflow: auto; display: block; -webkit-overflow-scrolling: touch; position: relative;\"> \n  <svg xmlns=\"http://www.w3.org/2000/svg\" role=\"img\" focusable=\"false\" viewbox=\"0 -716 4546.7 866\" aria-hidden=\"true\" style=\"-webkit-overflow-scrolling: touch; vertical-align: -0.339ex; width: 10.287ex; height: 1.959ex; max-width: 300% !important;\"> <g stroke=\"currentColor\" fill=\"currentColor\" stroke-width=\"0\" transform=\"matrix(1 0 0 -1 0 0)\"> \n    <g data-mml-node=\"math\"> \n     <g data-mml-node=\"msub\"> \n      <g data-mml-node=\"mi\"> \n       <path data-c=\"1D44B\" d=\"M42 0H40Q26 0 26 11Q26 15 29 27Q33 41 36 43T55 46Q141 49 190 98Q200 108 306 224T411 342Q302 620 297 625Q288 636 234 637H206Q200 643 200 645T202 664Q206 677 212 683H226Q260 681 347 681Q380 681 408 681T453 682T473 682Q490 682 490 671Q490 670 488 658Q484 643 481 640T465 637Q434 634 411 620L488 426L541 485Q646 598 646 610Q646 628 622 635Q617 635 609 637Q594 637 594 648Q594 650 596 664Q600 677 606 683H618Q619 683 643 683T697 681T738 680Q828 680 837 683H845Q852 676 852 672Q850 647 840 637H824Q790 636 763 628T722 611T698 593L687 584Q687 585 592 480L505 384Q505 383 536 304T601 142T638 56Q648 47 699 46Q734 46 734 37Q734 35 732 23Q728 7 725 4T711 1Q708 1 678 1T589 2Q528 2 496 2T461 1Q444 1 444 10Q444 11 446 25Q448 35 450 39T455 44T464 46T480 47T506 54Q523 62 523 64Q522 64 476 181L429 299Q241 95 236 84Q232 76 232 72Q232 53 261 47Q262 47 267 47T273 46Q276 46 277 46T280 45T283 42T284 35Q284 26 282 19Q279 6 276 4T261 1Q258 1 243 1T201 2T142 2Q64 2 42 0Z\" /> \n      </g> \n      <g data-mml-node=\"mn\" transform=\"translate(828, -150) scale(0.707)\"> \n       <path data-c=\"32\" d=\"M109 429Q82 429 66 447T50 491Q50 562 103 614T235 666Q326 666 387 610T449 465Q449 422 429 383T381 315T301 241Q265 210 201 149L142 93L218 92Q375 92 385 97Q392 99 409 186V189H449V186Q448 183 436 95T421 3V0H50V19V31Q50 38 56 46T86 81Q115 113 136 137Q145 147 170 174T204 211T233 244T261 278T284 308T305 340T320 369T333 401T340 431T343 464Q343 527 309 573T212 619Q179 619 154 602T119 569T109 550Q109 549 114 549Q132 549 151 535T170 489Q170 464 154 447T109 429Z\" /> \n      </g> \n     </g> \n     <g data-mml-node=\"mo\" transform=\"translate(1509.3, 0)\"> \n      <path data-c=\"3D\" d=\"M56 347Q56 360 70 367H707Q722 359 722 347Q722 336 708 328L390 327H72Q56 332 56 347ZM56 153Q56 168 72 173H708Q722 163 722 153Q722 140 707 133H70Q56 140 56 153Z\" /> \n     </g> \n     <g data-mml-node=\"mi\" transform=\"translate(2565.1, 0)\"> \n      <path data-c=\"1D434\" d=\"M208 74Q208 50 254 46Q272 46 272 35Q272 34 270 22Q267 8 264 4T251 0Q249 0 239 0T205 1T141 2Q70 2 50 0H42Q35 7 35 11Q37 38 48 46H62Q132 49 164 96Q170 102 345 401T523 704Q530 716 547 716H555H572Q578 707 578 706L606 383Q634 60 636 57Q641 46 701 46Q726 46 726 36Q726 34 723 22Q720 7 718 4T704 0Q701 0 690 0T651 1T578 2Q484 2 455 0H443Q437 6 437 9T439 27Q443 40 445 43L449 46H469Q523 49 533 63L521 213H283L249 155Q208 86 208 74ZM516 260Q516 271 504 416T490 562L463 519Q447 492 400 412L310 260L413 259Q516 259 516 260Z\" /> \n     </g> \n     <g data-mml-node=\"msub\" transform=\"translate(3315.1, 0)\"> \n      <g data-mml-node=\"mi\"> \n       <path data-c=\"1D44B\" d=\"M42 0H40Q26 0 26 11Q26 15 29 27Q33 41 36 43T55 46Q141 49 190 98Q200 108 306 224T411 342Q302 620 297 625Q288 636 234 637H206Q200 643 200 645T202 664Q206 677 212 683H226Q260 681 347 681Q380 681 408 681T453 682T473 682Q490 682 490 671Q490 670 488 658Q484 643 481 640T465 637Q434 634 411 620L488 426L541 485Q646 598 646 610Q646 628 622 635Q617 635 609 637Q594 637 594 648Q594 650 596 664Q600 677 606 683H618Q619 683 643 683T697 681T738 680Q828 680 837 683H845Q852 676 852 672Q850 647 840 637H824Q790 636 763 628T722 611T698 593L687 584Q687 585 592 480L505 384Q505 383 536 304T601 142T638 56Q648 47 699 46Q734 46 734 37Q734 35 732 23Q728 7 725 4T711 1Q708 1 678 1T589 2Q528 2 496 2T461 1Q444 1 444 10Q444 11 446 25Q448 35 450 39T455 44T464 46T480 47T506 54Q523 62 523 64Q522 64 476 181L429 299Q241 95 236 84Q232 76 232 72Q232 53 261 47Q262 47 267 47T273 46Q276 46 277 46T280 45T283 42T284 35Q284 26 282 19Q279 6 276 4T261 1Q258 1 243 1T201 2T142 2Q64 2 42 0Z\" /> \n      </g> \n      <g data-mml-node=\"mn\" transform=\"translate(828, -150) scale(0.707)\"> \n       <path data-c=\"31\" d=\"M213 578L200 573Q186 568 160 563T102 556H83V602H102Q149 604 189 617T245 641T273 663Q275 666 285 666Q294 666 302 660V361L303 61Q310 54 315 52T339 48T401 46H427V0H416Q395 3 257 3Q121 3 100 0H88V46H114Q136 46 152 46T177 47T193 50T201 52T207 57T213 61V578Z\" /> \n      </g> \n     </g> \n    </g> \n   </g> \n  </svg> \n </section></span> \n<p data-tool=\"mdnice编辑器\" style=\"padding-top: 8px; padding-bottom: 8px; margin: 0; line-height: 26px; color: black; font-size: 17px; word-spacing: 3px; letter-spacing: 1px;\">在 DMD 中，获取 Koopman 矩阵并执行预测任务并不困难。DMD 中最重要的工具是奇异值分解和特征值分解。要<strong style=\"font-weight: bold; color: black;\">计算 Koopman 矩阵</strong>，只需遵循两个步骤：</p> \n<ul data-tool=\"mdnice编辑器\" style=\"margin-top: 8px; margin-bottom: 8px; padding-left: 25px; color: black; list-style-type: disc;\"> \n <li> \n  <section style=\"margin-top: 5px; margin-bottom: 5px; line-height: 26px; text-align: left; color: rgb(1,1,1); font-weight: 500;\">\n    对数据矩阵***X1***进行奇异值分解： \n  </section></li> \n</ul> <span class=\"span-block-equation\" style=\"cursor:pointer\" data-tool=\"mdnice编辑器\"> \n <section class=\"block-equation\" width=\"full\" role=\"presentation\" data-formula=\"\\begin{equation}\nX_1 = U \\Sigma V^{\\top}\n\\end{equation}\n\" data-formula-type=\"block-equation\" style=\"display: block; text-align: center; overflow: auto; display: block; -webkit-overflow-scrolling: touch; min-width: 21.807ex; position: relative;\"> \n  <svg xmlns=\"http://www.w3.org/2000/svg\" role=\"img\" focusable=\"false\" aria-hidden=\"true\" style=\"-webkit-overflow-scrolling: touch; vertical-align: -0.719ex; min-width: 21.807ex; width: 100%; height: 2.569ex; max-width: 300% !important;\"> <g stroke=\"currentColor\" fill=\"currentColor\" stroke-width=\"0\" transform=\"matrix(1 0 0 -1 0 0) scale(0.016893) translate(0, -817.7)\"> \n    <g data-mml-node=\"math\"> \n     <g data-mml-node=\"mtable\" transform=\"translate(2078, 0) translate(-2078, 0)\"> \n      <g transform=\"translate(0 817.7) matrix(1 0 0 -1 0 0) scale(59.2)\"> \n       <svg data-table=\"true\" preserveaspectratio=\"xMidYMid\" viewbox=\"2741.3 -817.7 1 1135.3\" style=\"-webkit-overflow-scrolling: touch; max-width: 300% !important;\"> <g transform=\"matrix(1 0 0 -1 0 0)\"> \n         <g data-mml-node=\"mlabeledtr\" transform=\"translate(0, -67.7)\"> \n          <g data-mml-node=\"mtd\"> \n           <g data-mml-node=\"msub\"> \n            <g data-mml-node=\"mi\"> \n             <path data-c=\"1D44B\" d=\"M42 0H40Q26 0 26 11Q26 15 29 27Q33 41 36 43T55 46Q141 49 190 98Q200 108 306 224T411 342Q302 620 297 625Q288 636 234 637H206Q200 643 200 645T202 664Q206 677 212 683H226Q260 681 347 681Q380 681 408 681T453 682T473 682Q490 682 490 671Q490 670 488 658Q484 643 481 640T465 637Q434 634 411 620L488 426L541 485Q646 598 646 610Q646 628 622 635Q617 635 609 637Q594 637 594 648Q594 650 596 664Q600 677 606 683H618Q619 683 643 683T697 681T738 680Q828 680 837 683H845Q852 676 852 672Q850 647 840 637H824Q790 636 763 628T722 611T698 593L687 584Q687 585 592 480L505 384Q505 383 536 304T601 142T638 56Q648 47 699 46Q734 46 734 37Q734 35 732 23Q728 7 725 4T711 1Q708 1 678 1T589 2Q528 2 496 2T461 1Q444 1 444 10Q444 11 446 25Q448 35 450 39T455 44T464 46T480 47T506 54Q523 62 523 64Q522 64 476 181L429 299Q241 95 236 84Q232 76 232 72Q232 53 261 47Q262 47 267 47T273 46Q276 46 277 46T280 45T283 42T284 35Q284 26 282 19Q279 6 276 4T261 1Q258 1 243 1T201 2T142 2Q64 2 42 0Z\" /> \n            </g> \n            <g data-mml-node=\"mn\" transform=\"translate(828, -150) scale(0.707)\"> \n             <path data-c=\"31\" d=\"M213 578L200 573Q186 568 160 563T102 556H83V602H102Q149 604 189 617T245 641T273 663Q275 666 285 666Q294 666 302 660V361L303 61Q310 54 315 52T339 48T401 46H427V0H416Q395 3 257 3Q121 3 100 0H88V46H114Q136 46 152 46T177 47T193 50T201 52T207 57T213 61V578Z\" /> \n            </g> \n           </g> \n           <g data-mml-node=\"mo\" transform=\"translate(1509.3, 0)\"> \n            <path data-c=\"3D\" d=\"M56 347Q56 360 70 367H707Q722 359 722 347Q722 336 708 328L390 327H72Q56 332 56 347ZM56 153Q56 168 72 173H708Q722 163 722 153Q722 140 707 133H70Q56 140 56 153Z\" /> \n           </g> \n           <g data-mml-node=\"mi\" transform=\"translate(2565.1, 0)\"> \n            <path data-c=\"1D448\" d=\"M107 637Q73 637 71 641Q70 643 70 649Q70 673 81 682Q83 683 98 683Q139 681 234 681Q268 681 297 681T342 682T362 682Q378 682 378 672Q378 670 376 658Q371 641 366 638H364Q362 638 359 638T352 638T343 637T334 637Q295 636 284 634T266 623Q265 621 238 518T184 302T154 169Q152 155 152 140Q152 86 183 55T269 24Q336 24 403 69T501 205L552 406Q599 598 599 606Q599 633 535 637Q511 637 511 648Q511 650 513 660Q517 676 519 679T529 683Q532 683 561 682T645 680Q696 680 723 681T752 682Q767 682 767 672Q767 650 759 642Q756 637 737 637Q666 633 648 597Q646 592 598 404Q557 235 548 205Q515 105 433 42T263 -22Q171 -22 116 34T60 167V183Q60 201 115 421Q164 622 164 628Q164 635 107 637Z\" /> \n           </g> \n           <g data-mml-node=\"mi\" transform=\"translate(3332.1, 0)\"> \n            <path data-c=\"3A3\" d=\"M666 247Q664 244 652 126T638 4V0H351Q131 0 95 0T57 5V6Q54 12 57 17L73 36Q89 54 121 90T182 159L305 299L56 644L55 658Q55 677 60 681Q63 683 351 683H638V679Q640 674 652 564T666 447V443H626V447Q618 505 604 543T559 605Q529 626 478 631T333 637H294H189L293 494Q314 465 345 422Q400 346 400 340Q400 338 399 337L154 57Q407 57 428 58Q476 60 508 68T551 83T575 103Q595 125 608 162T624 225L626 251H666V247Z\" /> \n           </g> \n           <g data-mml-node=\"msup\" transform=\"translate(4054.1, 0)\"> \n            <g data-mml-node=\"mi\"> \n             <path data-c=\"1D449\" d=\"M52 648Q52 670 65 683H76Q118 680 181 680Q299 680 320 683H330Q336 677 336 674T334 656Q329 641 325 637H304Q282 635 274 635Q245 630 242 620Q242 618 271 369T301 118L374 235Q447 352 520 471T595 594Q599 601 599 609Q599 633 555 637Q537 637 537 648Q537 649 539 661Q542 675 545 679T558 683Q560 683 570 683T604 682T668 681Q737 681 755 683H762Q769 676 769 672Q769 655 760 640Q757 637 743 637Q730 636 719 635T698 630T682 623T670 615T660 608T652 599T645 592L452 282Q272 -9 266 -16Q263 -18 259 -21L241 -22H234Q216 -22 216 -15Q213 -9 177 305Q139 623 138 626Q133 637 76 637H59Q52 642 52 648Z\" /> \n            </g> \n            <g data-mml-node=\"TeXAtom\" transform=\"translate(828.3, 413) scale(0.707)\" data-mjx-texclass=\"ORD\"> \n             <g data-mml-node=\"mi\"> \n              <path data-c=\"22A4\" d=\"M55 642T55 648T59 659T66 666T71 668H708Q723 660 723 648T708 628H409V15Q402 2 391 0Q387 0 384 1T379 3T375 6T373 9T371 13T369 16V628H71Q70 628 67 630T59 637Z\" /> \n             </g> \n            </g> \n           </g> \n          </g> \n         </g> \n        </g> \n       </svg> \n       <svg data-labels=\"true\" preserveaspectratio=\"xMaxYMid\" viewbox=\"1278 -817.7 1 1135.3\" style=\"-webkit-overflow-scrolling: touch; max-width: 300% !important;\"> <g data-labels=\"true\" transform=\"matrix(1 0 0 -1 0 0)\"> \n         <g data-mml-node=\"mtd\" id=\"mjx-eqn-2\" transform=\"translate(0, -67.7)\"> \n          <g data-mml-node=\"mtext\"> \n           <path data-c=\"28\" d=\"M94 250Q94 319 104 381T127 488T164 576T202 643T244 695T277 729T302 750H315H319Q333 750 333 741Q333 738 316 720T275 667T226 581T184 443T167 250T184 58T225 -81T274 -167T316 -220T333 -241Q333 -250 318 -250H315H302L274 -226Q180 -141 137 -14T94 250Z\" /> \n           <path data-c=\"32\" d=\"M109 429Q82 429 66 447T50 491Q50 562 103 614T235 666Q326 666 387 610T449 465Q449 422 429 383T381 315T301 241Q265 210 201 149L142 93L218 92Q375 92 385 97Q392 99 409 186V189H449V186Q448 183 436 95T421 3V0H50V19V31Q50 38 56 46T86 81Q115 113 136 137Q145 147 170 174T204 211T233 244T261 278T284 308T305 340T320 369T333 401T340 431T343 464Q343 527 309 573T212 619Q179 619 154 602T119 569T109 550Q109 549 114 549Q132 549 151 535T170 489Q170 464 154 447T109 429Z\" transform=\"translate(389, 0)\" /> \n           <path data-c=\"29\" d=\"M60 749L64 750Q69 750 74 750H86L114 726Q208 641 251 514T294 250Q294 182 284 119T261 12T224 -76T186 -143T145 -194T113 -227T90 -246Q87 -249 86 -250H74Q66 -250 63 -250T58 -247T55 -238Q56 -237 66 -225Q221 -64 221 250T66 725Q56 737 55 738Q55 746 60 749Z\" transform=\"translate(889, 0)\" /> \n          </g> \n         </g> \n        </g> \n       </svg> \n      </g> \n     </g> \n    </g> \n   </g> \n  </svg> \n </section></span> \n<p data-tool=\"mdnice编辑器\" style=\"padding-top: 8px; padding-bottom: 8px; margin: 0; line-height: 26px; color: black; font-size: 17px; word-spacing: 3px; letter-spacing: 1px;\">其中<strong style=\"font-weight: bold; color: black;\"><em style=\"font-style: italic; color: black;\">U*<em style=\"font-style: italic; color: black;\">由左奇异向量组成，</em>V</em>由右奇异向量组成，</strong>Σ以其对角线上的奇异值组成。</p> \n<ul data-tool=\"mdnice编辑器\" style=\"margin-top: 8px; margin-bottom: 8px; padding-left: 25px; color: black; list-style-type: disc;\"> \n <li> \n  <section style=\"margin-top: 5px; margin-bottom: 5px; line-height: 26px; text-align: left; color: rgb(1,1,1); font-weight: 500;\">\n    实现具有特定预定义秩<em style=\"font-style: italic; color: black;\">r</em>的截断奇异值分解，并通过以下方式计算 Koopman 矩阵 \n  </section></li> \n</ul> <span class=\"span-block-equation\" style=\"cursor:pointer\" data-tool=\"mdnice编辑器\"> \n <section class=\"block-equation\" width=\"full\" role=\"presentation\" data-formula=\"\\begin{equation}\n\\tilde{A} = U_r^{\\top} X_2 V_r \\Sigma_r^{-1}\n\\end{equation}\n\" data-formula-type=\"block-equation\" style=\"display: block; text-align: center; overflow: auto; display: block; -webkit-overflow-scrolling: touch; min-width: 26.095ex; position: relative;\"> \n  <svg xmlns=\"http://www.w3.org/2000/svg\" role=\"img\" focusable=\"false\" aria-hidden=\"true\" style=\"-webkit-overflow-scrolling: touch; vertical-align: -0.83ex; min-width: 26.095ex; width: 100%; height: 2.791ex; max-width: 300% !important;\"> <g stroke=\"currentColor\" fill=\"currentColor\" stroke-width=\"0\" transform=\"matrix(1 0 0 -1 0 0) scale(0.016893) translate(0, -866.9)\"> \n    <g data-mml-node=\"math\"> \n     <g data-mml-node=\"mtable\" transform=\"translate(2078, 0) translate(-2078, 0)\"> \n      <g transform=\"translate(0 866.9) matrix(1 0 0 -1 0 0) scale(59.2)\"> \n       <svg data-table=\"true\" preserveaspectratio=\"xMidYMid\" viewbox=\"3689 -866.9 1 1233.8\" style=\"-webkit-overflow-scrolling: touch; max-width: 300% !important;\"> <g transform=\"matrix(1 0 0 -1 0 0)\"> \n         <g data-mml-node=\"mlabeledtr\" transform=\"translate(0, -112.1)\"> \n          <g data-mml-node=\"mtd\"> \n           <g data-mml-node=\"TeXAtom\" data-mjx-texclass=\"ORD\"> \n            <g data-mml-node=\"mover\"> \n             <g data-mml-node=\"mi\"> \n              <path data-c=\"1D434\" d=\"M208 74Q208 50 254 46Q272 46 272 35Q272 34 270 22Q267 8 264 4T251 0Q249 0 239 0T205 1T141 2Q70 2 50 0H42Q35 7 35 11Q37 38 48 46H62Q132 49 164 96Q170 102 345 401T523 704Q530 716 547 716H555H572Q578 707 578 706L606 383Q634 60 636 57Q641 46 701 46Q726 46 726 36Q726 34 723 22Q720 7 718 4T704 0Q701 0 690 0T651 1T578 2Q484 2 455 0H443Q437 6 437 9T439 27Q443 40 445 43L449 46H469Q523 49 533 63L521 213H283L249 155Q208 86 208 74ZM516 260Q516 271 504 416T490 562L463 519Q447 492 400 412L310 260L413 259Q516 259 516 260Z\" /> \n             </g> \n             <g data-mml-node=\"mo\" transform=\"translate(264, 561)\"> \n              <path data-c=\"7E\" d=\"M179 251Q164 251 151 245T131 234T111 215L97 227L83 238Q83 239 95 253T121 283T142 304Q165 318 187 318T253 300T320 282Q335 282 348 288T368 299T388 318L402 306L416 295Q375 236 344 222Q330 215 313 215Q292 215 248 233T179 251Z\" /> \n             </g> \n            </g> \n           </g> \n           <g data-mml-node=\"mo\" transform=\"translate(1041.8, 0)\"> \n            <path data-c=\"3D\" d=\"M56 347Q56 360 70 367H707Q722 359 722 347Q722 336 708 328L390 327H72Q56 332 56 347ZM56 153Q56 168 72 173H708Q722 163 722 153Q722 140 707 133H70Q56 140 56 153Z\" /> \n           </g> \n           <g data-mml-node=\"msubsup\" transform=\"translate(2097.6, 0)\"> \n            <g data-mml-node=\"mi\"> \n             <path data-c=\"1D448\" d=\"M107 637Q73 637 71 641Q70 643 70 649Q70 673 81 682Q83 683 98 683Q139 681 234 681Q268 681 297 681T342 682T362 682Q378 682 378 672Q378 670 376 658Q371 641 366 638H364Q362 638 359 638T352 638T343 637T334 637Q295 636 284 634T266 623Q265 621 238 518T184 302T154 169Q152 155 152 140Q152 86 183 55T269 24Q336 24 403 69T501 205L552 406Q599 598 599 606Q599 633 535 637Q511 637 511 648Q511 650 513 660Q517 676 519 679T529 683Q532 683 561 682T645 680Q696 680 723 681T752 682Q767 682 767 672Q767 650 759 642Q756 637 737 637Q666 633 648 597Q646 592 598 404Q557 235 548 205Q515 105 433 42T263 -22Q171 -22 116 34T60 167V183Q60 201 115 421Q164 622 164 628Q164 635 107 637Z\" /> \n            </g> \n            <g data-mml-node=\"TeXAtom\" transform=\"translate(821.2, 413) scale(0.707)\" data-mjx-texclass=\"ORD\"> \n             <g data-mml-node=\"mi\"> \n              <path data-c=\"22A4\" d=\"M55 642T55 648T59 659T66 666T71 668H708Q723 660 723 648T708 628H409V15Q402 2 391 0Q387 0 384 1T379 3T375 6T373 9T371 13T369 16V628H71Q70 628 67 630T59 637Z\" /> \n             </g> \n            </g> \n            <g data-mml-node=\"mi\" transform=\"translate(683, -247) scale(0.707)\"> \n             <path data-c=\"1D45F\" d=\"M21 287Q22 290 23 295T28 317T38 348T53 381T73 411T99 433T132 442Q161 442 183 430T214 408T225 388Q227 382 228 382T236 389Q284 441 347 441H350Q398 441 422 400Q430 381 430 363Q430 333 417 315T391 292T366 288Q346 288 334 299T322 328Q322 376 378 392Q356 405 342 405Q286 405 239 331Q229 315 224 298T190 165Q156 25 151 16Q138 -11 108 -11Q95 -11 87 -5T76 7T74 17Q74 30 114 189T154 366Q154 405 128 405Q107 405 92 377T68 316T57 280Q55 278 41 278H27Q21 284 21 287Z\" /> \n            </g> \n           </g> \n           <g data-mml-node=\"msub\" transform=\"translate(3518.9, 0)\"> \n            <g data-mml-node=\"mi\"> \n             <path data-c=\"1D44B\" d=\"M42 0H40Q26 0 26 11Q26 15 29 27Q33 41 36 43T55 46Q141 49 190 98Q200 108 306 224T411 342Q302 620 297 625Q288 636 234 637H206Q200 643 200 645T202 664Q206 677 212 683H226Q260 681 347 681Q380 681 408 681T453 682T473 682Q490 682 490 671Q490 670 488 658Q484 643 481 640T465 637Q434 634 411 620L488 426L541 485Q646 598 646 610Q646 628 622 635Q617 635 609 637Q594 637 594 648Q594 650 596 664Q600 677 606 683H618Q619 683 643 683T697 681T738 680Q828 680 837 683H845Q852 676 852 672Q850 647 840 637H824Q790 636 763 628T722 611T698 593L687 584Q687 585 592 480L505 384Q505 383 536 304T601 142T638 56Q648 47 699 46Q734 46 734 37Q734 35 732 23Q728 7 725 4T711 1Q708 1 678 1T589 2Q528 2 496 2T461 1Q444 1 444 10Q444 11 446 25Q448 35 450 39T455 44T464 46T480 47T506 54Q523 62 523 64Q522 64 476 181L429 299Q241 95 236 84Q232 76 232 72Q232 53 261 47Q262 47 267 47T273 46Q276 46 277 46T280 45T283 42T284 35Q284 26 282 19Q279 6 276 4T261 1Q258 1 243 1T201 2T142 2Q64 2 42 0Z\" /> \n            </g> \n            <g data-mml-node=\"mn\" transform=\"translate(828, -150) scale(0.707)\"> \n             <path data-c=\"32\" d=\"M109 429Q82 429 66 447T50 491Q50 562 103 614T235 666Q326 666 387 610T449 465Q449 422 429 383T381 315T301 241Q265 210 201 149L142 93L218 92Q375 92 385 97Q392 99 409 186V189H449V186Q448 183 436 95T421 3V0H50V19V31Q50 38 56 46T86 81Q115 113 136 137Q145 147 170 174T204 211T233 244T261 278T284 308T305 340T320 369T333 401T340 431T343 464Q343 527 309 573T212 619Q179 619 154 602T119 569T109 550Q109 549 114 549Q132 549 151 535T170 489Q170 464 154 447T109 429Z\" /> \n            </g> \n           </g> \n           <g data-mml-node=\"msub\" transform=\"translate(4750.4, 0)\"> \n            <g data-mml-node=\"mi\"> \n             <path data-c=\"1D449\" d=\"M52 648Q52 670 65 683H76Q118 680 181 680Q299 680 320 683H330Q336 677 336 674T334 656Q329 641 325 637H304Q282 635 274 635Q245 630 242 620Q242 618 271 369T301 118L374 235Q447 352 520 471T595 594Q599 601 599 609Q599 633 555 637Q537 637 537 648Q537 649 539 661Q542 675 545 679T558 683Q560 683 570 683T604 682T668 681Q737 681 755 683H762Q769 676 769 672Q769 655 760 640Q757 637 743 637Q730 636 719 635T698 630T682 623T670 615T660 608T652 599T645 592L452 282Q272 -9 266 -16Q263 -18 259 -21L241 -22H234Q216 -22 216 -15Q213 -9 177 305Q139 623 138 626Q133 637 76 637H59Q52 642 52 648Z\" /> \n            </g> \n            <g data-mml-node=\"mi\" transform=\"translate(583, -150) scale(0.707)\"> \n             <path data-c=\"1D45F\" d=\"M21 287Q22 290 23 295T28 317T38 348T53 381T73 411T99 433T132 442Q161 442 183 430T214 408T225 388Q227 382 228 382T236 389Q284 441 347 441H350Q398 441 422 400Q430 381 430 363Q430 333 417 315T391 292T366 288Q346 288 334 299T322 328Q322 376 378 392Q356 405 342 405Q286 405 239 331Q229 315 224 298T190 165Q156 25 151 16Q138 -11 108 -11Q95 -11 87 -5T76 7T74 17Q74 30 114 189T154 366Q154 405 128 405Q107 405 92 377T68 316T57 280Q55 278 41 278H27Q21 284 21 287Z\" /> \n            </g> \n           </g> \n           <g data-mml-node=\"msubsup\" transform=\"translate(5702.3, 0)\"> \n            <g data-mml-node=\"mi\"> \n             <path data-c=\"3A3\" d=\"M666 247Q664 244 652 126T638 4V0H351Q131 0 95 0T57 5V6Q54 12 57 17L73 36Q89 54 121 90T182 159L305 299L56 644L55 658Q55 677 60 681Q63 683 351 683H638V679Q640 674 652 564T666 447V443H626V447Q618 505 604 543T559 605Q529 626 478 631T333 637H294H189L293 494Q314 465 345 422Q400 346 400 340Q400 338 399 337L154 57Q407 57 428 58Q476 60 508 68T551 83T575 103Q595 125 608 162T624 225L626 251H666V247Z\" /> \n            </g> \n            <g data-mml-node=\"TeXAtom\" transform=\"translate(722, 413) scale(0.707)\" data-mjx-texclass=\"ORD\"> \n             <g data-mml-node=\"mo\"> \n              <path data-c=\"2212\" d=\"M84 237T84 250T98 270H679Q694 262 694 250T679 230H98Q84 237 84 250Z\" /> \n             </g> \n             <g data-mml-node=\"mn\" transform=\"translate(778, 0)\"> \n              <path data-c=\"31\" d=\"M213 578L200 573Q186 568 160 563T102 556H83V602H102Q149 604 189 617T245 641T273 663Q275 666 285 666Q294 666 302 660V361L303 61Q310 54 315 52T339 48T401 46H427V0H416Q395 3 257 3Q121 3 100 0H88V46H114Q136 46 152 46T177 47T193 50T201 52T207 57T213 61V578Z\" /> \n             </g> \n            </g> \n            <g data-mml-node=\"mi\" transform=\"translate(722, -247) scale(0.707)\"> \n             <path data-c=\"1D45F\" d=\"M21 287Q22 290 23 295T28 317T38 348T53 381T73 411T99 433T132 442Q161 442 183 430T214 408T225 388Q227 382 228 382T236 389Q284 441 347 441H350Q398 441 422 400Q430 381 430 363Q430 333 417 315T391 292T366 288Q346 288 334 299T322 328Q322 376 378 392Q356 405 342 405Q286 405 239 331Q229 315 224 298T190 165Q156 25 151 16Q138 -11 108 -11Q95 -11 87 -5T76 7T74 17Q74 30 114 189T154 366Q154 405 128 405Q107 405 92 377T68 316T57 280Q55 278 41 278H27Q21 284 21 287Z\" /> \n            </g> \n           </g> \n          </g> \n         </g> \n        </g> \n       </svg> \n       <svg data-labels=\"true\" preserveaspectratio=\"xMaxYMid\" viewbox=\"1278 -866.9 1 1233.8\" style=\"-webkit-overflow-scrolling: touch; max-width: 300% !important;\"> <g data-labels=\"true\" transform=\"matrix(1 0 0 -1 0 0)\"> \n         <g data-mml-node=\"mtd\" id=\"mjx-eqn-3\" transform=\"translate(0, -112.1)\"> \n          <g data-mml-node=\"mtext\"> \n           <path data-c=\"28\" d=\"M94 250Q94 319 104 381T127 488T164 576T202 643T244 695T277 729T302 750H315H319Q333 750 333 741Q333 738 316 720T275 667T226 581T184 443T167 250T184 58T225 -81T274 -167T316 -220T333 -241Q333 -250 318 -250H315H302L274 -226Q180 -141 137 -14T94 250Z\" /> \n           <path data-c=\"33\" d=\"M127 463Q100 463 85 480T69 524Q69 579 117 622T233 665Q268 665 277 664Q351 652 390 611T430 522Q430 470 396 421T302 350L299 348Q299 347 308 345T337 336T375 315Q457 262 457 175Q457 96 395 37T238 -22Q158 -22 100 21T42 130Q42 158 60 175T105 193Q133 193 151 175T169 130Q169 119 166 110T159 94T148 82T136 74T126 70T118 67L114 66Q165 21 238 21Q293 21 321 74Q338 107 338 175V195Q338 290 274 322Q259 328 213 329L171 330L168 332Q166 335 166 348Q166 366 174 366Q202 366 232 371Q266 376 294 413T322 525V533Q322 590 287 612Q265 626 240 626Q208 626 181 615T143 592T132 580H135Q138 579 143 578T153 573T165 566T175 555T183 540T186 520Q186 498 172 481T127 463Z\" transform=\"translate(389, 0)\" /> \n           <path data-c=\"29\" d=\"M60 749L64 750Q69 750 74 750H86L114 726Q208 641 251 514T294 250Q294 182 284 119T261 12T224 -76T186 -143T145 -194T113 -227T90 -246Q87 -249 86 -250H74Q66 -250 63 -250T58 -247T55 -238Q56 -237 66 -225Q221 -64 221 250T66 725Q56 737 55 738Q55 746 60 749Z\" transform=\"translate(889, 0)\" /> \n          </g> \n         </g> \n        </g> \n       </svg> \n      </g> \n     </g> \n    </g> \n   </g> \n  </svg> \n </section></span> \n<p data-tool=\"mdnice编辑器\" style=\"padding-top: 8px; padding-bottom: 8px; margin: 0; line-height: 26px; color: black; font-size: 17px; word-spacing: 3px; letter-spacing: 1px;\">如上所述，DMD 可以通过动态模式探索可解释的时间行为。如果要<strong style=\"font-weight: bold; color: black;\">计算动态模式</strong>，请按照以下步骤操作：</p> \n<ul data-tool=\"mdnice编辑器\" style=\"margin-top: 8px; margin-bottom: 8px; padding-left: 25px; color: black; list-style-type: disc;\"> \n <li> \n  <section style=\"margin-top: 5px; margin-bottom: 5px; line-height: 26px; text-align: left; color: rgb(1,1,1); font-weight: 500;\">\n    对 Koopman 矩阵执行特征值分解： \n  </section></li> \n</ul> <span class=\"span-block-equation\" style=\"cursor:pointer\" data-tool=\"mdnice编辑器\"> \n <section class=\"block-equation\" width=\"full\" role=\"presentation\" data-formula=\"\\begin{equation}\n\\tilde{A} = Q \\Phi Q^{\\top}\n\\end{equation}\n\n\" data-formula-type=\"block-equation\" style=\"display: block; text-align: center; overflow: auto; display: block; -webkit-overflow-scrolling: touch; min-width: 20.719ex; position: relative;\"> \n  <svg xmlns=\"http://www.w3.org/2000/svg\" role=\"img\" focusable=\"false\" aria-hidden=\"true\" style=\"-webkit-overflow-scrolling: touch; vertical-align: -0.825ex; min-width: 20.719ex; width: 100%; height: 2.781ex; max-width: 300% !important;\"> <g stroke=\"currentColor\" fill=\"currentColor\" stroke-width=\"0\" transform=\"matrix(1 0 0 -1 0 0) scale(0.016893) translate(0, -864.5)\"> \n    <g data-mml-node=\"math\"> \n     <g data-mml-node=\"mtable\" transform=\"translate(2078, 0) translate(-2078, 0)\"> \n      <g transform=\"translate(0 864.5) matrix(1 0 0 -1 0 0) scale(59.2)\"> \n       <svg data-table=\"true\" preserveaspectratio=\"xMidYMid\" viewbox=\"2500.8 -864.5 1 1229\" style=\"-webkit-overflow-scrolling: touch; max-width: 300% !important;\"> <g transform=\"matrix(1 0 0 -1 0 0)\"> \n         <g data-mml-node=\"mlabeledtr\" transform=\"translate(0, -114.5)\"> \n          <g data-mml-node=\"mtd\"> \n           <g data-mml-node=\"TeXAtom\" data-mjx-texclass=\"ORD\"> \n            <g data-mml-node=\"mover\"> \n             <g data-mml-node=\"mi\"> \n              <path data-c=\"1D434\" d=\"M208 74Q208 50 254 46Q272 46 272 35Q272 34 270 22Q267 8 264 4T251 0Q249 0 239 0T205 1T141 2Q70 2 50 0H42Q35 7 35 11Q37 38 48 46H62Q132 49 164 96Q170 102 345 401T523 704Q530 716 547 716H555H572Q578 707 578 706L606 383Q634 60 636 57Q641 46 701 46Q726 46 726 36Q726 34 723 22Q720 7 718 4T704 0Q701 0 690 0T651 1T578 2Q484 2 455 0H443Q437 6 437 9T439 27Q443 40 445 43L449 46H469Q523 49 533 63L521 213H283L249 155Q208 86 208 74ZM516 260Q516 271 504 416T490 562L463 519Q447 492 400 412L310 260L413 259Q516 259 516 260Z\" /> \n             </g> \n             <g data-mml-node=\"mo\" transform=\"translate(264, 561)\"> \n              <path data-c=\"7E\" d=\"M179 251Q164 251 151 245T131 234T111 215L97 227L83 238Q83 239 95 253T121 283T142 304Q165 318 187 318T253 300T320 282Q335 282 348 288T368 299T388 318L402 306L416 295Q375 236 344 222Q330 215 313 215Q292 215 248 233T179 251Z\" /> \n             </g> \n            </g> \n           </g> \n           <g data-mml-node=\"mo\" transform=\"translate(1041.8, 0)\"> \n            <path data-c=\"3D\" d=\"M56 347Q56 360 70 367H707Q722 359 722 347Q722 336 708 328L390 327H72Q56 332 56 347ZM56 153Q56 168 72 173H708Q722 163 722 153Q722 140 707 133H70Q56 140 56 153Z\" /> \n           </g> \n           <g data-mml-node=\"mi\" transform=\"translate(2097.6, 0)\"> \n            <path data-c=\"1D444\" d=\"M399 -80Q399 -47 400 -30T402 -11V-7L387 -11Q341 -22 303 -22Q208 -22 138 35T51 201Q50 209 50 244Q50 346 98 438T227 601Q351 704 476 704Q514 704 524 703Q621 689 680 617T740 435Q740 255 592 107Q529 47 461 16L444 8V3Q444 2 449 -24T470 -66T516 -82Q551 -82 583 -60T625 -3Q631 11 638 11Q647 11 649 2Q649 -6 639 -34T611 -100T557 -165T481 -194Q399 -194 399 -87V-80ZM636 468Q636 523 621 564T580 625T530 655T477 665Q429 665 379 640Q277 591 215 464T153 216Q153 110 207 59Q231 38 236 38V46Q236 86 269 120T347 155Q372 155 390 144T417 114T429 82T435 55L448 64Q512 108 557 185T619 334T636 468ZM314 18Q362 18 404 39L403 49Q399 104 366 115Q354 117 347 117Q344 117 341 117T337 118Q317 118 296 98T274 52Q274 18 314 18Z\" /> \n           </g> \n           <g data-mml-node=\"mi\" transform=\"translate(2888.6, 0)\"> \n            <path data-c=\"3A6\" d=\"M312 622Q310 623 307 625T303 629T297 631T286 634T270 635T246 636T211 637H184V683H196Q220 680 361 680T526 683H538V637H511Q468 637 447 635T422 631T411 622V533L425 531Q525 519 595 466T665 342Q665 301 642 267T583 209T506 172T425 152L411 150V61Q417 55 421 53T447 48T511 46H538V0H526Q502 3 361 3T196 0H184V46H211Q231 46 245 46T270 47T286 48T297 51T303 54T307 57T312 61V150H310Q309 151 289 153T232 166T160 195Q149 201 136 210T103 238T69 284T56 342Q56 414 128 467T294 530Q309 532 310 533H312V622ZM170 342Q170 207 307 188H312V495H309Q301 495 282 491T231 469T186 423Q170 389 170 342ZM415 188Q487 199 519 236T551 342Q551 384 539 414T507 459T470 481T434 491T415 495H410V188H415Z\" /> \n           </g> \n           <g data-mml-node=\"msup\" transform=\"translate(3610.6, 0)\"> \n            <g data-mml-node=\"mi\"> \n             <path data-c=\"1D444\" d=\"M399 -80Q399 -47 400 -30T402 -11V-7L387 -11Q341 -22 303 -22Q208 -22 138 35T51 201Q50 209 50 244Q50 346 98 438T227 601Q351 704 476 704Q514 704 524 703Q621 689 680 617T740 435Q740 255 592 107Q529 47 461 16L444 8V3Q444 2 449 -24T470 -66T516 -82Q551 -82 583 -60T625 -3Q631 11 638 11Q647 11 649 2Q649 -6 639 -34T611 -100T557 -165T481 -194Q399 -194 399 -87V-80ZM636 468Q636 523 621 564T580 625T530 655T477 665Q429 665 379 640Q277 591 215 464T153 216Q153 110 207 59Q231 38 236 38V46Q236 86 269 120T347 155Q372 155 390 144T417 114T429 82T435 55L448 64Q512 108 557 185T619 334T636 468ZM314 18Q362 18 404 39L403 49Q399 104 366 115Q354 117 347 117Q344 117 341 117T337 118Q317 118 296 98T274 52Q274 18 314 18Z\" /> \n            </g> \n            <g data-mml-node=\"TeXAtom\" transform=\"translate(791, 413) scale(0.707)\" data-mjx-texclass=\"ORD\"> \n             <g data-mml-node=\"mi\"> \n              <path data-c=\"22A4\" d=\"M55 642T55 648T59 659T66 666T71 668H708Q723 660 723 648T708 628H409V15Q402 2 391 0Q387 0 384 1T379 3T375 6T373 9T371 13T369 16V628H71Q70 628 67 630T59 637Z\" /> \n             </g> \n            </g> \n           </g> \n          </g> \n         </g> \n        </g> \n       </svg> \n       <svg data-labels=\"true\" preserveaspectratio=\"xMaxYMid\" viewbox=\"1278 -864.5 1 1229\" style=\"-webkit-overflow-scrolling: touch; max-width: 300% !important;\"> <g data-labels=\"true\" transform=\"matrix(1 0 0 -1 0 0)\"> \n         <g data-mml-node=\"mtd\" id=\"mjx-eqn-4\" transform=\"translate(0, -114.5)\"> \n          <g data-mml-node=\"mtext\"> \n           <path data-c=\"28\" d=\"M94 250Q94 319 104 381T127 488T164 576T202 643T244 695T277 729T302 750H315H319Q333 750 333 741Q333 738 316 720T275 667T226 581T184 443T167 250T184 58T225 -81T274 -167T316 -220T333 -241Q333 -250 318 -250H315H302L274 -226Q180 -141 137 -14T94 250Z\" /> \n           <path data-c=\"34\" d=\"M462 0Q444 3 333 3Q217 3 199 0H190V46H221Q241 46 248 46T265 48T279 53T286 61Q287 63 287 115V165H28V211L179 442Q332 674 334 675Q336 677 355 677H373L379 671V211H471V165H379V114Q379 73 379 66T385 54Q393 47 442 46H471V0H462ZM293 211V545L74 212L183 211H293Z\" transform=\"translate(389, 0)\" /> \n           <path data-c=\"29\" d=\"M60 749L64 750Q69 750 74 750H86L114 726Q208 641 251 514T294 250Q294 182 284 119T261 12T224 -76T186 -143T145 -194T113 -227T90 -246Q87 -249 86 -250H74Q66 -250 63 -250T58 -247T55 -238Q56 -237 66 -225Q221 -64 221 250T66 725Q56 737 55 738Q55 746 60 749Z\" transform=\"translate(889, 0)\" /> \n          </g> \n         </g> \n        </g> \n       </svg> \n      </g> \n     </g> \n    </g> \n   </g> \n  </svg> \n </section></span> \n<p data-tool=\"mdnice编辑器\" style=\"padding-top: 8px; padding-bottom: 8px; margin: 0; line-height: 26px; color: black; font-size: 17px; word-spacing: 3px; letter-spacing: 1px;\">现在，我们有了 VAR(1) 中提到的系数矩阵***A。***因此，可以实现时间序列预测任务。这是 DMD 算法的 Python 代码。我们使用 Numpy 重现它，它将很容易理解。</p> \n<pre class=\"custom\" data-tool=\"mdnice编辑器\" style=\"margin-top: 10px; margin-bottom: 10px;\"><code class=\"hljs\" style=\"overflow-x: auto; padding: 16px; color: #333; background: #f8f8f8; display: -webkit-box; font-family: Operator Mono, Consolas, Monaco, Menlo, monospace; border-radius: 0px; font-size: 12px; -webkit-overflow-scrolling: touch;\">import&nbsp;numpy&nbsp;as&nbsp;np<br>def&nbsp;DMD(data,&nbsp;r):<br>&nbsp;&nbsp;&nbsp;&nbsp;<span class=\"hljs-string\" style=\"color: #d14; line-height: 26px;\">\"\"</span><span class=\"hljs-string\" style=\"color: #d14; line-height: 26px;\">\"Dynamic&nbsp;Mode&nbsp;Decomposition&nbsp;(DMD)&nbsp;algorithm.\"</span><span class=\"hljs-string\" style=\"color: #d14; line-height: 26px;\">\"\"</span><br>&nbsp;&nbsp;&nbsp;&nbsp;<br>&nbsp;&nbsp;&nbsp;&nbsp;<span class=\"hljs-comment\" style=\"color: #998; font-style: italic; line-height: 26px;\">##&nbsp;Build&nbsp;data&nbsp;matrices</span><br>&nbsp;&nbsp;&nbsp;&nbsp;X1&nbsp;=&nbsp;data[:,&nbsp;:&nbsp;-1]<br>&nbsp;&nbsp;&nbsp;&nbsp;X2&nbsp;=&nbsp;data[:,&nbsp;1&nbsp;:]<br>&nbsp;&nbsp;&nbsp;&nbsp;<span class=\"hljs-comment\" style=\"color: #998; font-style: italic; line-height: 26px;\">##&nbsp;Perform&nbsp;singular&nbsp;value&nbsp;decomposition&nbsp;on&nbsp;X1</span><br>&nbsp;&nbsp;&nbsp;&nbsp;u,&nbsp;s,&nbsp;v&nbsp;=&nbsp;np.linalg.svd(X1,&nbsp;full_matrices&nbsp;=&nbsp;False)<br>&nbsp;&nbsp;&nbsp;&nbsp;<span class=\"hljs-comment\" style=\"color: #998; font-style: italic; line-height: 26px;\">##&nbsp;Compute&nbsp;the&nbsp;Koopman&nbsp;matrix</span><br>&nbsp;&nbsp;&nbsp;&nbsp;A_tilde&nbsp;=&nbsp;u[:,&nbsp;:&nbsp;r].conj().T&nbsp;@&nbsp;X2&nbsp;@&nbsp;v[:&nbsp;r,&nbsp;:].conj().T&nbsp;*&nbsp;np.reciprocal(s[:&nbsp;r])<br>&nbsp;&nbsp;&nbsp;&nbsp;<span class=\"hljs-comment\" style=\"color: #998; font-style: italic; line-height: 26px;\">##&nbsp;Perform&nbsp;eigenvalue&nbsp;decomposition&nbsp;on&nbsp;A_tilde</span><br>&nbsp;&nbsp;&nbsp;&nbsp;Phi,&nbsp;Q&nbsp;=&nbsp;np.linalg.eig(A_tilde)<br>&nbsp;&nbsp;&nbsp;&nbsp;<span class=\"hljs-comment\" style=\"color: #998; font-style: italic; line-height: 26px;\">##&nbsp;Compute&nbsp;the&nbsp;coefficient&nbsp;matrix</span><br>&nbsp;&nbsp;&nbsp;&nbsp;Psi&nbsp;=&nbsp;X2&nbsp;@&nbsp;v[:&nbsp;r,&nbsp;:].conj().T&nbsp;@&nbsp;np.diag(np.reciprocal(s[:&nbsp;r]))&nbsp;@&nbsp;Q<br>&nbsp;&nbsp;&nbsp;&nbsp;A&nbsp;=&nbsp;Psi&nbsp;@&nbsp;np.diag(Phi)&nbsp;@&nbsp;np.linalg.pinv(Psi)<br>&nbsp;&nbsp;&nbsp;&nbsp;<br>&nbsp;&nbsp;&nbsp;&nbsp;<span class=\"hljs-built_in\" style=\"color: #0086b3; line-height: 26px;\">return</span>&nbsp;A_tilde,&nbsp;Phi,&nbsp;A<br></code></pre> \n<p data-tool=\"mdnice编辑器\" style=\"padding-top: 8px; padding-bottom: 8px; margin: 0; line-height: 26px; color: black; font-size: 17px; word-spacing: 3px; letter-spacing: 1px;\">输出包括库普曼矩阵、特征值和系数矩阵。</p> \n<h2 data-tool=\"mdnice编辑器\" style=\"margin-top: 30px; margin-bottom: 15px; padding: 0px; font-weight: bold; color: black; font-size: 22px;\"><span class=\"prefix\" style=\"display: none;\"></span><span class=\"content\" style=\"background-color: #F7D3CC; color: #FFF; padding: 5px 15px; border-radius: 1px;\">地学实例</span><span class=\"suffix\"></span></h2> \n<p data-tool=\"mdnice编辑器\" style=\"padding-top: 8px; padding-bottom: 8px; margin: 0; line-height: 26px; color: black; font-size: 17px; word-spacing: 3px; letter-spacing: 1px;\">给一个具体案例，预测土壤水时间序列</p> \n<p data-tool=\"mdnice编辑器\" style=\"padding-top: 8px; padding-bottom: 8px; margin: 0; line-height: 26px; color: black; font-size: 17px; word-spacing: 3px; letter-spacing: 1px;\">首先是DMD方法</p> \n<pre class=\"custom\" data-tool=\"mdnice编辑器\" style=\"margin-top: 10px; margin-bottom: 10px;\"><code class=\"hljs\" style=\"overflow-x: auto; padding: 16px; color: #333; background: #f8f8f8; display: -webkit-box; font-family: Operator Mono, Consolas, Monaco, Menlo, monospace; border-radius: 0px; font-size: 12px; -webkit-overflow-scrolling: touch;\">import&nbsp;numpy&nbsp;as&nbsp;np<br>def&nbsp;DMD4cast(data,&nbsp;r,&nbsp;pred_step):<br>&nbsp;&nbsp;&nbsp;&nbsp;N,&nbsp;T&nbsp;=&nbsp;data.shape<br>&nbsp;&nbsp;&nbsp;&nbsp;_,&nbsp;_,&nbsp;A&nbsp;=&nbsp;DMD(data,&nbsp;r)<br>&nbsp;&nbsp;&nbsp;&nbsp;mat&nbsp;=&nbsp;np.append(data,&nbsp;np.zeros((N,&nbsp;pred_step)),&nbsp;axis&nbsp;=&nbsp;1)<br>&nbsp;&nbsp;&nbsp;&nbsp;<span class=\"hljs-keyword\" style=\"color: #333; font-weight: bold; line-height: 26px;\">for</span>&nbsp;s&nbsp;<span class=\"hljs-keyword\" style=\"color: #333; font-weight: bold; line-height: 26px;\">in</span>&nbsp;range(pred_step):<br>&nbsp;&nbsp;&nbsp;&nbsp;&nbsp;&nbsp;&nbsp;&nbsp;mat[:,&nbsp;T&nbsp;+&nbsp;s]&nbsp;=&nbsp;(A&nbsp;@&nbsp;mat[:,&nbsp;T&nbsp;+&nbsp;s&nbsp;-&nbsp;1]).real<br>&nbsp;&nbsp;&nbsp;&nbsp;<span class=\"hljs-built_in\" style=\"color: #0086b3; line-height: 26px;\">return</span>&nbsp;mat[:,&nbsp;-&nbsp;pred_step&nbsp;:]<br></code></pre> \n<p data-tool=\"mdnice编辑器\" style=\"padding-top: 8px; padding-bottom: 8px; margin: 0; line-height: 26px; color: black; font-size: 17px; word-spacing: 3px; letter-spacing: 1px;\">然后是数据</p> \n<pre class=\"custom\" data-tool=\"mdnice编辑器\" style=\"margin-top: 10px; margin-bottom: 10px;\"><code class=\"hljs\" style=\"overflow-x: auto; padding: 16px; color: #333; background: #f8f8f8; display: -webkit-box; font-family: Operator Mono, Consolas, Monaco, Menlo, monospace; border-radius: 0px; font-size: 12px; -webkit-overflow-scrolling: touch;\">import&nbsp;pandas&nbsp;as&nbsp;pd<br>data&nbsp;=&nbsp;pd.read_csv(<span class=\"hljs-string\" style=\"color: #d14; line-height: 26px;\">'/home/mw/input/geo9882/geo.csv'</span>)<br>data<br><br>import&nbsp;matplotlib.pyplot&nbsp;as&nbsp;plt<br>plt.plot(data[<span class=\"hljs-string\" style=\"color: #d14; line-height: 26px;\">'soil_water'</span>])<br>plt.show()<br><br></code></pre> \n<figure data-tool=\"mdnice编辑器\" style=\"margin: 0; margin-top: 10px; margin-bottom: 10px; display: flex; flex-direction: column; justify-content: center; align-items: center;\"> \n <img src=\"https://files.mdnice.com/user/40204/093168ff-3fd8-4ca7-9fab-6afd245c3b6b.png\" alt style=\"display: block; margin: 0 auto; max-width: 100%; border-radius: 10px; border: 3px solid #F7D3CC;\"> \n</figure> \n<p data-tool=\"mdnice编辑器\" style=\"padding-top: 8px; padding-bottom: 8px; margin: 0; line-height: 26px; color: black; font-size: 17px; word-spacing: 3px; letter-spacing: 1px;\">土壤水序列如图，可以看到预测还是相对困难。</p> \n<p data-tool=\"mdnice编辑器\" style=\"padding-top: 8px; padding-bottom: 8px; margin: 0; line-height: 26px; color: black; font-size: 17px; word-spacing: 3px; letter-spacing: 1px;\">我们想要预测序列的后几十个值</p> \n<pre class=\"custom\" data-tool=\"mdnice编辑器\" style=\"margin-top: 10px; margin-bottom: 10px;\"><code class=\"hljs\" style=\"overflow-x: auto; padding: 16px; color: #333; background: #f8f8f8; display: -webkit-box; font-family: Operator Mono, Consolas, Monaco, Menlo, monospace; border-radius: 0px; font-size: 12px; -webkit-overflow-scrolling: touch;\">data['soil_water'][-13:]\n</code></pre> \n<figure data-tool=\"mdnice编辑器\" style=\"margin: 0; margin-top: 10px; margin-bottom: 10px; display: flex; flex-direction: column; justify-content: center; align-items: center;\"> \n <img src=\"https://files.mdnice.com/user/40204/be16850f-cb18-4e01-8423-b9270dd9f088.png\" alt style=\"display: block; margin: 0 auto; max-width: 100%; border-radius: 10px; border: 3px solid #F7D3CC;\"> \n</figure> \n<pre class=\"custom\" data-tool=\"mdnice编辑器\" style=\"margin-top: 10px; margin-bottom: 10px;\"><code class=\"hljs\" style=\"overflow-x: auto; padding: 16px; color: #333; background: #f8f8f8; display: -webkit-box; font-family: Operator Mono, Consolas, Monaco, Menlo, monospace; border-radius: 0px; font-size: 12px; -webkit-overflow-scrolling: touch;\">X&nbsp;=&nbsp;np.zeros((2,&nbsp;131))<br>X[0,&nbsp;:]&nbsp;=&nbsp;data[<span class=\"hljs-string\" style=\"color: #d14; line-height: 26px;\">'soil_water'</span>][:-13]<br>X[1,&nbsp;:]&nbsp;=&nbsp;data[<span class=\"hljs-string\" style=\"color: #d14; line-height: 26px;\">'soil_water'</span>][1:-12]<br>pred_step&nbsp;=&nbsp;12<br>r&nbsp;=&nbsp;2<br>mat_hat&nbsp;=&nbsp;DMD4cast(X,&nbsp;r,&nbsp;pred_step)<br><span class=\"hljs-built_in\" style=\"color: #0086b3; line-height: 26px;\">print</span>(mat_hat)<br></code></pre> \n<figure data-tool=\"mdnice编辑器\" style=\"margin: 0; margin-top: 10px; margin-bottom: 10px; display: flex; flex-direction: column; justify-content: center; align-items: center;\"> \n <img src=\"https://files.mdnice.com/user/40204/4002e66c-fbb1-4fda-bb16-4533842ee22a.png\" alt style=\"display: block; margin: 0 auto; max-width: 100%; border-radius: 10px; border: 3px solid #F7D3CC;\"> \n</figure> \n<p data-tool=\"mdnice编辑器\" style=\"padding-top: 8px; padding-bottom: 8px; margin: 0; line-height: 26px; color: black; font-size: 17px; word-spacing: 3px; letter-spacing: 1px;\">模型成功返回了结果，基本一致。</p>",
                "title": "利用动态模式分解简单实现时间序列预测",
                "categoryId": 3,
                "categoryName": "人工智能",
                "tagId": 116,
                "tagName": "机器学习",
                "userId": 40204,
                "userOutId": "706880289656",
                "username": "LonghaoWang",
                "avatar": "https://files.mdnice.com/pic/20a54d83-6259-4b66-8689-c8ce6b9e8616.jpg",
                "description": "多元时间序列预测的动态模式分解动态模式分解(DMD)是一种数据驱动的降维算法，由PeterSchmid于2008年开发类似于矩阵分解和主成分分析(PCA)算法。给定一个多变量时间序列数据集，DMD计算",
                "level": 2,
                "publishTime": "2024/10/18",
                "readingNum": 6,
                "likeNum": 0,
                "introduction": null,
                "followWords": null,
                "followPic": null,
                "isFollowing": false,
                "isLike": false,
                "isSelf": false,
                "type": 1,
                "isVisible": true,
                "invisibleReason": null,
                "writingColumn": {
                    "columnOutId": "ffe00cb8fcef4def81f23ac36ce58752",
                    "name": "默认专栏",
                    "briefIntro": "这是一个默认专栏",
                    "cover": "https://files.mdnice.com/common/community/default-column-cover.jpg",
                    "writingNum": 63,
                    "createTime": "2024-08-06 19:05"
                }
            }
        },
        "__N_SSP": true
    },
    "page": "/writing/[id]",
    "query": {
        "id": "1376620d9137402e94ac1c959558f146"
    },
    "buildId": "ErZPkD4oq6iwH2nj6Dpcx",
    "isFallback": false,
    "gssp": true,
    "appGip": true
}